README.md
setup.py
PiHole_api.egg-info/PKG-INFO
PiHole_api.egg-info/SOURCES.txt
PiHole_api.egg-info/dependency_links.txt
PiHole_api.egg-info/requires.txt
PiHole_api.egg-info/top_level.txt
pihole/__init__.py
pihole/main.py