Metadata-Version: 2.1
Name: PiHole-api
Version: 2.6
Summary: A python3 wrapper for the pihole api that aims to eventually be a full replacement for the AdminLTE web panel
Home-page: https://github.com/Ewpratten/PiHole-api
Author: Evan Pratten
Author-email: ewpratten@gmail.com
License: MIT
Platform: UNKNOWN
Classifier: Programming Language :: Python :: 3
Classifier: License :: OSI Approved :: MIT License
Classifier: Operating System :: OS Independent
Classifier: Development Status :: 5 - Production/Stable
